highlevel/__init__.py
highlevel/client.py
highlevel/exceptions.py
highlevel_python-0.1.4.dist-info/METADATA
highlevel_python-0.1.4.dist-info/WHEEL
highlevel_python-0.1.4.dist-info/RECORD
