Metadata-Version: 2.1
Name: highlevel-python
Version: 0.1.4
Summary: API wrapper for Highlevel written in Python
License: MIT
Author: Gearplug Team
Author-email: apps@gearplug.io
Requires-Python: >=3.7,<4.0
Classifier: License :: OSI Approved :: MIT License
Classifier: Programming Language :: Python :: 3
Classifier: Programming Language :: Python :: 3.7
Classifier: Programming Language :: Python :: 3.8
Classifier: Programming Language :: Python :: 3.9
Classifier: Programming Language :: Python :: 3.10
Classifier: Programming Language :: Python :: 3.11
Classifier: Programming Language :: Python :: 3.12
Requires-Dist: requests (>=2.26.0,<3.0.0)
Requires-Dist: requests_oauthlib (>=1.3.1,<2.0.0)
